Metadata-Version: 1.1
Name: cuda4py
Version: 1.4.4
Summary: CUDA cffi bindings and helper classes
Home-page: https://github.com/ajkxyz/cuda4py
Author: Samsung Electronics Co.,Ltd.
Author-email: a.kazantsev@samsung.com
License: Simplified BSD
Download-URL: https://github.com/ajkxyz/cuda4py
Keywords: CUDA,cuBLAS,cuDNN,cuFFT,cuRAND,cuda4py
Platform: UNKNOWN
Classifier: Development Status :: 4 - Beta
Classifier: Environment :: Console
Classifier: Intended Audience :: Developers
Classifier: License :: OSI Approved :: BSD License
Classifier: Operating System :: POSIX
Classifier: Programming Language :: Python :: 2.7
Classifier: Programming Language :: Python :: 3.2
Classifier: Programming Language :: Python :: 3.3
Classifier: Programming Language :: Python :: 3.4
Classifier: Programming Language :: Python :: 3.5
Classifier: Programming Language :: Python :: 3.6
Classifier: Topic :: Software Development :: Libraries
